<?xml version="1.0" encoding="UTF-8" ?><root><temp type="float">5.7</temp><feels_like type="float">1.13</feels_like><pressure type="float">1022.39</pressure><humidity type="float">57.43</humidity><dew_point type="float">-1.88</dew_point><clouds type="float">20.1</clouds><wind_speed type="float">3.28</wind_speed><wind_deg type="float">356.73</wind_deg><wind_gust type="float">4.51</wind_gust><weather type="str">[{&apos;id&apos;: 801, &apos;main&apos;: &apos;Clouds&apos;, &apos;description&apos;: &apos;few clouds&apos;, &apos;icon&apos;: &apos;02n&apos;}]</weather><rain_over_last_1h type="float">0.27</rain_over_last_1h><visibility type="float">10000.0</visibility></root>